digixt_pipeline_template/__init__.py
digixt_pipeline_template/__main__.py
digixt_pipeline_template/main.py
digixt_pipeline_template/project_structure_generator.py
digixt_pipeline_template/pyspark_template/README.md
digixt_pipeline_template/pyspark_template/common_utils/__init__.py
digixt_pipeline_template/pyspark_template/common_utils/flows/__init__.py
digixt_pipeline_template/pyspark_template/common_utils/flows/common_dag_module.py
digixt_pipeline_template/pyspark_template/common_utils/flows/custom_operator.py
digixt_pipeline_template/pyspark_template/common_utils/flows/email_alert_notification.py
digixt_pipeline_template/pyspark_template/common_utils/scripts/__init__.py
digixt_pipeline_template/pyspark_template/common_utils/scripts/batch_calculator_utils.py
digixt_pipeline_template/pyspark_template/common_utils/scripts/common_utilities.py
digixt_pipeline_template/pyspark_template/common_utils/scripts/creds_loader.py
digixt_pipeline_template/pyspark_template/common_utils/scripts/data/__init__.py
digixt_pipeline_template/pyspark_template/common_utils/scripts/data/common_data_utilities.py
digixt_pipeline_template/pyspark_template/common_utils/scripts/db_operations/__init__.py
digixt_pipeline_template/pyspark_template/common_utils/scripts/db_operations/db_operations.py
digixt_pipeline_template/pyspark_template/common_utils/scripts/db_operations/db_operations_factory.py
digixt_pipeline_template/pyspark_template/common_utils/scripts/helper/__init__.py
digixt_pipeline_template/pyspark_template/common_utils/scripts/helper/common_helper_utilities.py
digixt_pipeline_template/pyspark_template/common_utils/scripts/s3/__init__.py
digixt_pipeline_template/pyspark_template/common_utils/scripts/s3/common_s3_utilities.py
digixt_pipeline_template/pyspark_template/config/employee_data_schema.json
digixt_pipeline_template/pyspark_template/config/pyspark_template.json
digixt_pipeline_template/pyspark_template/flows/pyspark_template.py
digixt_pipeline_template-1.4.1.dist-info/METADATA
digixt_pipeline_template-1.4.1.dist-info/WHEEL
digixt_pipeline_template-1.4.1.dist-info/entry_points.txt
digixt_pipeline_template-1.4.1.dist-info/top_level.txt
digixt_pipeline_template-1.4.1.dist-info/RECORD
