Metadata-Version: 2.4
Name: digixt-pipeline-template
Version: 1.4.1
Summary: A template generator for PySpark projects, streamlining the setup process with predefined structures and configurations.
Author: Merhawi Kiflemariam
Author-email: merhawi@saal.ai
Classifier: Programming Language :: Python :: 3
Classifier: License :: OSI Approved :: MIT License
Classifier: Operating System :: OS Independent
Dynamic: author
Dynamic: author-email
Dynamic: classifier
Dynamic: description
Dynamic: description-content-type
Dynamic: summary
